<Root>

        <commands>
		<cmd name="TasksNewTask" pixtype="pixbuf"
		 _tip="Create a new task" verb="TasksNewTask"/>
		<cmd name="TasksDelete" _label="Delete" pixtype="stock" pixname="Trash"
		 _tip="Delete selected tasks" verb="TasksDelete"
		 accel="Delete" sensitive="0"/>

		<cmd name="TasksCut" pixtype="stock" pixname="Cut"
		 _tip="Cut selected task" verb="TasksCut" accel="*Control*x"/>
		<cmd name="TasksCopy" pixtype="stock" pixname="Copy"
		 _tip="Copy selected task" verb="TasksCopy" accel="*Control*c"/>
		<cmd name="TasksPaste" pixtype="stock" pixname="Paste"
		 _tip="Paste task from the clipboard" verb="TasksPaste" accel="*Control*v"/>

		<cmd name="TasksSettings" _tip="Configure the task view's settings"/>
  	</commands>
  
	<menu>
		<submenu name="File">

                        <submenu name="New">
				<placeholder name="NewFirstItem">
	  				<menuitem name="NewTask"
	  				verb="TasksNewTask"
					_label="_Task"
	                                accel="*Control*n"
					pixtype="pixbuf"/>
	                        </placeholder>
	                </submenu>
      
			<placeholder name="FileOps">
				
				<menuitem name="TasksSaveAs" verb=""
				_label="_Save As..."
				_tip="Save task as something else"
                                accel="*Control*a"/>

			</placeholder>

			<placeholder name="Print">

				<menuitem name="Print Preview" verb="TasksPrintPreview"
				_label="Print Pre_view"
				pixtype="pixbuf"/>

				<menuitem name="Print" verb="TasksPrint"
				_label="_Print"
				pixtype="pixbuf"
				accel="*Control*p"/>
				
			</placeholder>

		</submenu>

		<submenu name="Edit">

			<menuitem name="Cut" verb="TasksCut" _label="C_ut"/>
			<menuitem name="Copy" verb="TasksCopy" _label="_Copy"/>
			<menuitem name="Paste" verb="TasksPaste" _label="_Paste"/>
			<menuitem name="Delete" verb="TasksDelete"
			_label="_Delete"/>

		</submenu>

		<submenu name="Tools">

			<placeholder name="Component">
				<menuitem name="TasksSettings"
				 _label="Tasks Settings"
				 verb="TasksSettings" pixtype="pixbuf"/>
			</placeholder>

		</submenu>
	</menu>

	<dockitem name="Toolbar">
		<toolitem name="New" _label="New Task" verb="TasksNewTask"
		priority="1" pixtype="pixbuf"/>

	  	<separator/>

		<toolitem name="Print" _label="Print"
		_tip="Print" verb="TasksPrint"
		pixtype="pixbuf"/>

		<separator/>

		<toolitem name="Delete" verb="TasksDelete"/>

	</dockitem>

</Root>
